rabity/__init__.py
rabity/bot.py
rabity/ui.py
rabity/utils.py
rabity-0.8.4.dist-info/LICENSE
rabity-0.8.4.dist-info/METADATA
rabity-0.8.4.dist-info/WHEEL
rabity-0.8.4.dist-info/top_level.txt
rabity-0.8.4.dist-info/RECORD
