Metadata-Version: 2.1
Name: rabity
Version: 0.8.4
Summary: a library for creating websites
Author: Parsa
Author-email: mehr2.business@example.com
Classifier: Programming Language :: Python :: 3
Classifier: License :: OSI Approved :: MIT License
Classifier: Operating System :: OS Independent
Requires-Python: >=3.6
License-File: LICENSE
Requires-Dist: flask
Requires-Dist: colorama
Requires-Dist: zenora
Requires-Dist: customtkinter
Requires-Dist: tqdm
